<AanleveringInformatieObject xmlns="https://standaarden.overheid.nl/lvbb/stop/aanlevering/"
                             schemaversie="1.1.0">
   <InformatieObjectVersie>
      <ExpressionIdentificatie xmlns="https://standaarden.overheid.nl/stop/imop/data/">
         <FRBRWork>/join/id/regdata/gm0307/2019/Centrumgebied-intr-ini</FRBRWork>
         <FRBRExpression>/join/id/regdata/gm0307/2019/Centrumgebied-intr-ini/nld@2019-06-18;3520</FRBRExpression>
         <soortWork>/join/id/stop/work_010</soortWork>
      </ExpressionIdentificatie>
      <InformatieObjectVersieMetadata xmlns="https://standaarden.overheid.nl/stop/imop/data/">
         <heeftGeboorteregeling>/akn/nl/act/gm0307/2019/reg0001-intr-ini</heeftGeboorteregeling>
         <heeftBestanden>
            <heeftBestand>
               <Bestand>
                  <bestandsnaam>Centrumgebied.gml</bestandsnaam>
                  <hash>c69fd6caaa1d662a0bfd1641940b0ff93431afa28f4c7472910dd832561cea062ecc45138c2560a1f1626fa34e61afbbf7ec562fad937cdfd442a4d65499d683</hash>
               </Bestand>
            </heeftBestand>
         </heeftBestanden>
      </InformatieObjectVersieMetadata>
      <InformatieObjectMetadata xmlns="https://standaarden.overheid.nl/stop/imop/data/">
         <eindverantwoordelijke>/tooi/id/gemeente/gm0307</eindverantwoordelijke>
         <maker>/tooi/id/gemeente/gm0307</maker>
         <alternatieveTitels>
            <alternatieveTitel>Centrumgebied</alternatieveTitel>
         </alternatieveTitels>
         <naamInformatieObject>Centrumgebied</naamInformatieObject>
         <officieleTitel>/join/id/regdata/gm0307/2019/Centrumgebied-intr-ini</officieleTitel>
         <publicatieinstructie>TeConsolideren</publicatieinstructie>
         <formaatInformatieobject>/join/id/stop/informatieobject/gio_002</formaatInformatieobject>
      </InformatieObjectMetadata>
   </InformatieObjectVersie>
</AanleveringInformatieObject>
